Workbook

Sheet Company_Profile
A1: FIELD | B1: VALUE
A2: Company Name | B2: MOLE MINI-FINANCE
A3: Registration No | B3: 2026/PNG/FIN/001
A4: Business Type | B4: Mini Finance / Loan Services
A5: Address | B5: VANIMO, Sandaun Province, Papua New Guinea
A6: Contact Email | B6: info@molefinance.pg
A7: Phone | B7: +675 7172 0062 / +675 8249 3350
A8: Website | B8: mole-finance.com/pg
A9: Mission Statement | B9:  empower clients by offering quick and reliable financial support,  ensuring they can manage unexpected expenses to sustain their livelihood,  improve their overall quality of life, and  building long term relationships
A10: Vision
A11: Core Values | B11: • Integrity - Conducting Business honestly, ethically, and transparently • Customer Focus - Putting the needs of our clients first • Confidentiality – Protecting client information and privacy • Accessibility – Providing simple and convenient financial services • Responsibility – Promoting responsible borrowing and lending practices • Excellence – Delivering quality service and continuous improvement

Sheet CLIENT_MASTER
A1: CLIENT NO | B1: FULL NAME | C1: SEX | D1: DATE OF BIRTH | E1: PHONE | F1: PLACE OF RESIDENCE | G1: EMAIL ADDRESS | H1: NEXT OF KIN NAME | I1: RELATIONSHIP | J1: NEXT OF KIN PHONE NO | K1: EMPLOYMENT SECTOR | L1: EMPLOYER NAME | M1: JOB TITLE | N1: SALARY DEDUCTION FREQUENCY | O1: PAYROLL DEDUCTION AVAILABLE | P1: BANK ACCOUNT CONFIRMED | Q1: KYC NOTES
A2: CL-0001 | B2: Camilus Dominic | C2: M | D2: 26885 | E2: 701765546 | F2: Yawa P/S | G2: camilusdominic18@gmail.com | H2: Linda Dominic | I2: Spouse | J2: 709751874 | K2: Public | L2: Education | M2: Teacher | N2: Fortnightly | O2: Y | P2: Y | Q2: Verified
A3: CL-0002 | B3: Ricky Jolgai | C3: M | D3: 36130 | E3: 702284584 | F3: Yawa P/S | H3: Simby Jolgai | I3: Spouse | J3: 708120557 | K3: Public | L3: Education | M3: Teacher | N3: Fortnightly | O3: Y | P3: Y | Q3: Verified
A4: CL-0003 | B4: Simeon Kaipo | C4: M | D4: 32818 | E4: 702159698 | F4: Yawa P/S | H4: Callyn Kaipo | I4: Spouse | J4: 704013538 | K4: Public | L4: Education | M4: Teacher | N4: Fortnightly | O4: Y | P4: Y | Q4: Verified
A5: CL-0004 | B5: Josek Yuwal | C5: M | D5: 34666 | E5: 702242043 | F5: Yawa P/S | H5: Jean Yuwal | I5: Spouse | J5: 704621286 | K5: Public | L5: Education | M5: Teacher | N5: Fortnightly | O5: Y | P5: Y | Q5: Verified
A6: CL-0005 | B6: Bob Waiyoi | C6: M | D6: 36302 | E6: 704586745 | F6: Yawa P/S | H6: Jane Waiyoi | I6: Spouse | J6: 707967132 | K6: Public | L6: Education | M6: Teacher | N6: Fortnightly | O6: Y | P6: Y | Q6: Verified
A7: CL-0006 | B7: Rayleen Edai | C7: F | D7: 37291 | E7: 706113372 | F7: Teiri P/S | H7: Nelson Melu | I7: Spouse | J7: 708651309 | K7: Public | L7: Education | M7: Teacher | N7: Fortnightly | O7: Y | P7: Y | Q7: Verified
A8: CL-0007 | B8: Ruth Nali | C8: F | D8: 39702 | E8: 702570236 | F8: Teiri P/S | H8: James nali | I8: Spouse | J8: 707233556 | K8: Public | L8: Education | M8: Teacher | N8: Fortnightly | O8: Y | P8: Y | Q8: Verified
A9: CL-0008 | B9: Peter Fango | C9: M | D9: 38305 | E9: 705070560 | F9: Teiri P/S | H9: Rose Fango | I9: Spouse | J9: 702255783 | K9: Public | L9: Education | M9: Teacher | N9: Fortnightly | O9: Y | P9: Y | Q9: Verified
A10: CL-0009 | B10: Lucy Pita | C10: F | D10: 37795 | E10: 706594212 | F10: Teiri P/S | H10: Harry Pita | I10: Spouse | J10: 709491514 | K10: Public | L10: Education | M10: Teacher | N10: Fortnightly | O10: Y | P10: Y | Q10: Verified
A11: CL-0010 | B11: Gibson Melu | C11: M | D11: 39275 | E11: 71720062 | F11: Teiri P/S | H11: Sebby Melu | I11: Father | J11: 79954719 | K11: Public | L11: Education | M11: Teacher | N11: Fortnightly | O11: Y | P11: Y | Q11: Verified

Sheet LOAN_APPLICATION
A1: Loan App No | B1: Client No | C1: Loan Type | D1: Amount Requested | E1: Purpose Details | F1: Application Date | G1: Documents Received | H1: Verification Status | I1: Approval Status | J1: Approved Amount | K1: Approved Date | L1: Disbursement Date | M1: Interest Rate | N1: Repayment Period (Paydays) | O1: Total Repayment | P1: Installment Amount | Q1: Repayment Start Date | R1: Officer/Approver | S1: Notes
A2: LN-0001 | B2: CL-0001 | C2: Salary Advance | D2: 1000 | E2: Emergency Expense | F2: 46023 | G2: Y | H2: Verified | I2: Approved | J2: 1000 | K2: 2026 | L2: 2026 | M2: 0.5 | N2: 4 | O2: =J2*(1+M2) -> 1500 | P2: =O2/N2 -> 375
A3: LN-0002 | B3: CL-0002 | C3: Salary Advance | D3: 500 | E3: Personal | F3: 46023 | G3: Y | H3: Verified | I3: Approved | J3: 500 | K3: 46024 | L3: 46025 | M3: 0.2 | N3: 1 | O3: 600 | P3: 600 | Q3: 46039 | R3: Admin
A4: LN-0003 | B4: CL-0003 | C4: Salary Advance | D4: 1500 | E4: Personal | F4: 46023 | G4: Y | H4: Verified | I4: Approved | J4: 1500 | K4: 46024 | L4: 46025 | M4: 0.2 | N4: 1 | O4: 1800 | P4: 1800 | Q4: 46039 | R4: Admin
A5: LN-0004 | B5: CL-0004 | C5: Salary Advance | D5: 800 | E5: Personal | F5: 46023 | G5: Y | H5: Verified | I5: Approved | J5: 800 | K5: 46024 | L5: 46025 | M5: 0.4 | N5: 3 | O5: 1120 | P5: 373.33333 | Q5: 46039 | R5: Admin
A6: LN-0005 | B6: CL-0005 | C6: Salary Advance | D6: 500 | E6: Personal | F6: 46023 | G6: Y | H6: Verified | I6: Approved | J6: 500 | K6: 46024 | L6: 46025 | M6: 0.3 | N6: 2 | O6: 650 | P6: 325 | Q6: 46039 | R6: Admin
A7: LN-0006 | B7: CL-0006 | C7: Salary Advance | D7: 2500 | E7: Personal | F7: 46023 | G7: Y | H7: Verified | I7: Approved | J7: 2500 | K7: 46024 | L7: 46025 | M7: 0.3 | N7: 2 | O7: 3250 | P7: 1625 | Q7: 46039 | R7: Admin
A8: LN-0007 | B8: CL-0007 | C8: Salary Advance | D8: 1500 | E8: Personal | F8: 46023 | G8: Y | H8: Verified | I8: Approved | J8: 1500 | K8: 46024 | L8: 46025 | M8: 0.5 | N8: 4 | O8: 2250 | P8: 562.5 | Q8: 46039 | R8: Admin
A9: LN-0008 | B9: CL-0008 | C9: Salary Advance | D9: 800 | E9: Personal | F9: 46023 | G9: Y | H9: Verified | I9: Approved | J9: 800 | K9: 46024 | L9: 46025 | M9: 0.4 | N9: 3 | O9: 1120 | P9: 373.33333 | Q9: 46039 | R9: Admin
A10: LN-0009 | B10: CL-0009 | C10: Salary Advance | D10: 500 | E10: Personal | F10: 46023 | G10: Y | H10: Verified | I10: Approved | J10: 500 | K10: 46024 | L10: 46025 | M10: 0.2 | N10: 1 | O10: 600 | P10: 600 | Q10: 46039 | R10: Admin
A11: LN-0010 | B11: CL-0010 | C11: Salary Advance | D11: 500 | E11: Personal | F11: 46023 | G11: y | H11: Verified | I11: Approved | J11: 500 | K11: 46024 | L11: 46025 | M11: 0.2 | N11: 1 | O11: 600 | P11: 600 | Q11: 42761 | R11: Admin

Sheet REPAYMENT_SCHEDULE
A1: Repayment ID | B1: Loan App No | C1: Due Date | D1: Due Amount | E1: Paid Amount | F1: Payment Method | G1: Payment Date | H1: Status | I1: Late fees/ Interest | J1: Notes | K1: Column1 | L1: Column2
A2: RP-0001-4 | B2: LN-0001 | C2: 46039 | D2: 375 | E2: 375 | F2: Fortnightly | G2: 46039 | H2: Pending | I2: 0
A3: RP-0002-1 | B3: LN-0002 | C3: 46039 | D3: 600 | E3: 600 | F3: Fortnightly | G3: 46039 | H3: Paid | I3: 0
A4: RP-0003-1 | B4: LN-0003 | C4: 46039 | D4: 1800 | E4: 1800 | F4: Fortnightly | G4: 46039 | H4: Paid | I4: 0
A5: RP-0004-3 | B5: LN-0004 | C5: 46053 | D5: 373.33333 | E5: 373.33333 | F5: Fortnightly | G5: 46039 | H5: Pending | I5: 0
A6: RP-0005-2 | B6: LN-0005 | C6: 46067 | D6: 325 | E6: 325 | F6: Fortnightly | G6: 42761 | H6: Pending | I6: 0
A7: RP-0006-2 | B7: LN-0006 | C7: 46039 | D7: 1625 | E7: 1625 | F7: Fortnightly | G7: 46039 | H7: Paid | I7: 0
A8: RP-0007-4 | B8: LN-0007 | C8: 46053 | D8: 562.5 | E8: 562.5 | F8: Fortnightly | G8: 46039 | H8: Pending | I8: 0
A9: RP-0008-3 | B9: LN-0008 | C9: 46039 | D9: 373.33333 | E9: 1625 | F9: Fortnightly | G9: 46039 | H9: Pending | I9: 0
A10: RP-0009-1 | B10: LN-0009 | C10: 46053 | D10: 600 | E10: 600 | F10: Fortnightly | G10: 46039 | H10: Paid | I10: 0
A11: RP-0010-1 | B11: LN-0010 | C11: 46053 | D11: 600 | E11: 600 | F11: Fortnightly | G11: 46039 | H11: Paid | I11: 0

Sheet RISK_AND_COLLECTION
B2: Column1 | C2: Column2 | D2: Column3 | E2: Column4 | F2: Column5
B3: Loan_ID | C3: Risk_Level | D3: Collection_Action | E3: Notes | F3: Comments
B4: L001 | C4: Low | D4: Reminder SMS | E4: Client pays regularly
B5: L002 | C5: Medium | D5: Phone Call | E5: Payment overdue
B6: L003 | C6: High | D6: Legal Notice | E6: Loan declined | F6: risky
B7: L004 | C7: Low | D7: Reminder SMS | E7: Small loan | F7: client cooperative
B8: L005 | C8: Low | D8: Email Reminder | E8: Client consistent with payments
B9: L006 | C9: Medium | D9: Phone Call | E9: Pending approval | F9: needs follow-up
B10: L007 | C10: High | D10: Legal Notice | E10: Declined loan | F10: high risk
B11: L008 | C11: Low | D11: Reminder SMS | E11: Quick repayment expected
B12: L009 | C12: Medium | D12: Phone Call | E12: Payment delayed
B13: L010 | C13: Low | D13: Email Reminder | E13: Client reliable

Sheet LOAN_CALCULATOR
B2: Loan Amount | C2: Interest Rate | D2: Paydays/Forthnights | E2: Forthnightly Payment | F2: Total Repayment
B3: K100 | C3: 0.2 | D3: 1 | E3: K20 | F3: K120
B4: K200 | C4: 0.2 | D4: 1 | E4: K40 | F4: K240
B5: K300 | C5: 0.2 | D5: 1 | E5: K60 | F5: K360
B6: K300 | C6: 0.3 | D6: 2 | E6: K90 | F6: K390
B7: K300 | C7: 0.4 | D7: 3 | E7: K120 | F7: K420
B8: K300 | C8: 0.5 | D8: 4 | E8: K150 | F8: K450
B9: K400 | C9: 0.2 | D9: 1 | E9: K80 | F9: K480
B10: K400 | C10: 0.3 | D10: 2 | E10: K120 | F10: K420
B11: K400 | C11: 0.4 | D11: 3 | E11: K160 | F11: K560
B12: K400 | C12: 0.5 | D12: 4 | E12: K200 | F12: K600
B13: K600 | C13: 0.2 | D13: 1 | E13: K120 | F13: K720
B14: K600 | C14: 0.3 | D14: 2 | E14: K180 | F14: K780
... B48: K3000 | C48: 0.5 | D48: 4 | E48: K500 | F48: K2500

Sheet SUMMARYCLIENT
A1: CLIENT NO | B1: FULL NAME | C1: LOAN APPLICATION NO | D1: LOAN AMOUNT | E1: APPROVED AMOUNT | F1: INTEREST RATE | G1: REPAYMENT PERIOD PAYDAYS | H1: TOTAL REPAYMENT | I1: AMOUNT PAID | J1: OUTSTANDING BALANCE | K1: REPAYMENT STATUS | L1: OCCUPATION | M1: EMPLOYER NAME | N1: WORK LOCATION | O1: EMAIL ADDRESS | P1: PHONE NO | Q1: NEXT OF KIN NAME | R1: RELATIONSHIP | S1: NEXT OF KIN PHONE NO
A2: CL-0001 | B2: CAMILUS DOMINIC | C2: LN-0001 | D2: =VLOOKUP(Table7[[#This Row],[LOAN APPLICATION NO]],LOAN_APPLICATION!A:P,4,FALSE) -> 1000 | E2: =VLOOKUP(Table7[[#This Row],[LOAN APPLICATION NO]],LOAN_APPLICATION!A:P,10,FALSE) -> 1000 | F2: =VLOOKUP(Table7[[#This Row],[LOAN APPLICATION NO]],LOAN_APPLICATION!A:P,13,FALSE) -> 0.5 | G2: =VLOOKUP(Table7[[#This Row],[LOAN APPLICATION NO]],LOAN_APPLICATION!A:P,14,FALSE) -> 4 | H2: =VLOOKUP(Table7[[#This Row],[LOAN APPLICATION NO]],LOAN_APPLICATION!A:P,15,FALSE) -> 1500 | I2: =SUMIF(REPAYMENT_SCHEDULE!B:B,Table7[[#This Row],[LOAN APPLICATION NO]],REPAYMENT_SCHEDULE!F:F) -> 0 | J2: =Table7[[#This Row],[TOTAL REPAYMENT]]-Table7[[#This Row],[AMOUNT PAID]] -> 1500 | K2: =IF(Table7[[#This Row],[OUTSTANDING BALANCE]]=0,"Completed","Pending") -> Pending | L2: =VLOOKUP(Table7[[#This Row],[CLIENT NO]],CLIENT_MASTER!A:O,12,FALSE) -> Education | M2: =VLOOKUP(Table7[[#This Row],[CLIENT NO]],CLIENT_MASTER!A:O,11,FALSE) -> Public | N2: =VLOOKUP(Table7[[#This Row],[CLIENT NO]],CLIENT_MASTER!A:O,6,FALSE) -> Yawa P/S | O2: camilusdominic18@gmail.com | P2: =VLOOKUP(Table7[[#This Row],[CLIENT NO]],CLIENT_MASTER!A:O,5,FALSE) -> 701765546 | Q2: =VLOOKUP(Table7[[#This Row],[CLIENT NO]],CLIENT_MASTER!A:O,8,FALSE) -> Linda Dominic | R2: =VLOOKUP(Table7[[#This Row],[CLIENT NO]],CLIENT_MASTER!A:O,9,FALSE) -> Spouse | S2: =VLOOKUP(Table7[[#This Row],[CLIENT NO]],CLIENT_MASTER!A:O,10,FALSE) -> 709751874
A3: CL-0002 | B3: RICKY JOLGAI | C3: LN-0002 | D3: =VLOOKUP(Table7[[#This Row],[LOAN APPLICATION NO]],LOAN_APPLICATION!A:P,4,FALSE) -> 500 | E3: =VLOOKUP(Table7[[#This Row],[LOAN APPLICATION NO]],LOAN_APPLICATION!A:P,10,FALSE) -> 500 | F3: =VLOOKUP(Table7[[#This Row],[LOAN APPLICATION NO]],LOAN_APPLICATION!A:P,13,FALSE) -> 0.2 | G3: =VLOOKUP(Table7[[#This Row],[LOAN APPLICATION NO]],LOAN_APPLICATION!A:P,14,FALSE) -> 1 | H3: =VLOOKUP(Table7[[#This Row],[LOAN APPLICATION NO]],LOAN_APPLICATION!A:P,15,FALSE) -> 600 | I3: =SUMIF(REPAYMENT_SCHEDULE!B:B,Table7[[#This Row],[LOAN APPLICATION NO]],REPAYMENT_SCHEDULE!F:F) -> 0 | J3: =Table7[[#This Row],[TOTAL REPAYMENT]]-Table7[[#This Row],[AMOUNT PAID]] -> 600 | K3: =IF(Table7[[#This Row],[OUTSTANDING BALANCE]]=0,"Completed","Pending") -> Pending | L3: =VLOOKUP(Table7[[#This Row],[CLIENT NO]],CLIENT_MASTER!A:O,12,FALSE) -> Education | M3: =VLOOKUP(Table7[[#This Row],[CLIENT NO]],CLIENT_MASTER!A:O,11,FALSE) -> Public | N3: =VLOOKUP(Table7[[#This Row],[CLIENT NO]],CLIENT_MASTER!A:O,6,FALSE) -> Yawa P/S | P3: =VLOOKUP(Table7[[#This Row],[CLIENT NO]],CLIENT_MASTER!A:O,5,FALSE) -> 702284584 | Q3: =VLOOKUP(Table7[[#This Row],[CLIENT NO]],CLIENT_MASTER!A:O,8,FALSE) -> Simby Jolgai | R3: =VLOOKUP(Table7[[#This Row],[CLIENT NO]],CLIENT_MASTER!A:O,9,FALSE) -> Spouse | S3: =S2 -> 709751874
A4: CL-0003 | B4: Simeon Kaipo | C4: LN-0003 | D4: =VLOOKUP(Table7[[#This Row],[LOAN APPLICATION NO]],LOAN_APPLICATION!A:P,4,FALSE) -> 1500 | E4: =VLOOKUP(Table7[[#This Row],[LOAN APPLICATION NO]],LOAN_APPLICATION!A:P,10,FALSE) -> 1500 | F4: =VLOOKUP(Table7[[#This Row],[LOAN APPLICATION NO]],LOAN_APPLICATION!A:P,13,FALSE) -> 0.2 | G4: =VLOOKUP(Table7[[#This Row],[LOAN APPLICATION NO]],LOAN_APPLICATION!A:P,14,FALSE) -> 1 | H4: =VLOOKUP(Table7[[#This Row],[LOAN APPLICATION NO]],LOAN_APPLICATION!A:P,15,FALSE) -> 1800 | I4: =SUMIF(REPAYMENT_SCHEDULE!B:B,Table7[[#This Row],[LOAN APPLICATION NO]],REPAYMENT_SCHEDULE!F:F) -> 0 | J4: =Table7[[#This Row],[TOTAL REPAYMENT]]-Table7[[#This Row],[AMOUNT PAID]] -> 1800 | K4: =IF(Table7[[#This Row],[OUTSTANDING BALANCE]]=0,"Completed","Pending") -> Pending | L4: =VLOOKUP(Table7[[#This Row],[CLIENT NO]],CLIENT_MASTER!A:O,12,FALSE) -> Education | M4: =VLOOKUP(Table7[[#This Row],[CLIENT NO]],CLIENT_MASTER!A:O,11,FALSE) -> Public | N4: =VLOOKUP(Table7[[#This Row],[CLIENT NO]],CLIENT_MASTER!A:O,6,FALSE) -> Yawa P/S | P4: =VLOOKUP(Table7[[#This Row],[CLIENT NO]],CLIENT_MASTER!A:O,5,FALSE) -> 702159698 | Q4: =VLOOKUP(Table7[[#This Row],[CLIENT NO]],CLIENT_MASTER!A:O,8,FALSE) -> Callyn Kaipo | R4: =VLOOKUP(Table7[[#This Row],[CLIENT NO]],CLIENT_MASTER!A:O,9,FALSE) -> Spouse | S4: =VLOOKUP(Table7[[#This Row],[CLIENT NO]],CLIENT_MASTER!A:O,10,FALSE) -> 704013538
A5: CL-0004 | B5: Josek Yuwal | C5: LN-0004 | D5: =VLOOKUP(Table7[[#This Row],[LOAN APPLICATION NO]],LOAN_APPLICATION!A:P,4,FALSE) -> 800 | E5: =VLOOKUP(Table7[[#This Row],[LOAN APPLICATION NO]],LOAN_APPLICATION!A:P,10,FALSE) -> 800 | F5: =VLOOKUP(Table7[[#This Row],[LOAN APPLICATION NO]],LOAN_APPLICATION!A:P,13,FALSE) -> 0.4 | G5: =VLOOKUP(Table7[[#This Row],[LOAN APPLICATION NO]],LOAN_APPLICATION!A:P,14,FALSE) -> 3 | H5: =VLOOKUP(Table7[[#This Row],[LOAN APPLICATION NO]],LOAN_APPLICATION!A:P,15,FALSE) -> 1120 | I5: =SUMIF(REPAYMENT_SCHEDULE!B:B,Table7[[#This Row],[LOAN APPLICATION NO]],REPAYMENT_SCHEDULE!F:F) -> 0 | J5: =Table7[[#This Row],[TOTAL REPAYMENT]]-Table7[[#This Row],[AMOUNT PAID]] -> 1120 | K5: =IF(Table7[[#This Row],[OUTSTANDING BALANCE]]=0,"Completed","Pending") -> Pending | L5: =VLOOKUP(Table7[[#This Row],[CLIENT NO]],CLIENT_MASTER!A:O,12,FALSE) -> Education | M5: =VLOOKUP(Table7[[#This Row],[CLIENT NO]],CLIENT_MASTER!A:O,11,FALSE) -> Public | N5: =VLOOKUP(Table7[[#This Row],[CLIENT NO]],CLIENT_MASTER!A:O,6,FALSE) -> Yawa P/S | P5: =VLOOKUP(Table7[[#This Row],[CLIENT NO]],CLIENT_MASTER!A:O,5,FALSE) -> 702242043 | Q5: =VLOOKUP(Table7[[#This Row],[CLIENT NO]],CLIENT_MASTER!A:O,8,FALSE) -> Jean Yuwal | R5: =VLOOKUP(Table7[[#This Row],[CLIENT NO]],CLIENT_MASTER!A:O,9,FALSE) -> Spouse | S5: =VLOOKUP(Table7[[#This Row],[CLIENT NO]],CLIENT_MASTER!A:O,10,FALSE) -> 704621286
A6: CL-0005 | B6: Bob Waiyoi | C6: LN-0005 | D6: =VLOOKUP(Table7[[#This Row],[LOAN APPLICATION NO]],LOAN_APPLICATION!A:P,4,FALSE) -> 500 | E6: =VLOOKUP(Table7[[#This Row],[LOAN APPLICATION NO]],LOAN_APPLICATION!A:P,10,FALSE) -> 500 | F6: =VLOOKUP(Table7[[#This Row],[LOAN APPLICATION NO]],LOAN_APPLICATION!A:P,13,FALSE) -> 0.3 | G6: =VLOOKUP(Table7[[#This Row],[LOAN APPLICATION NO]],LOAN_APPLICATION!A:P,14,FALSE) -> 2 | H6: =VLOOKUP(Table7[[#This Row],[LOAN APPLICATION NO]],LOAN_APPLICATION!A:P,15,FALSE) -> 650 | I6: =SUMIF(REPAYMENT_SCHEDULE!B:B,Table7[[#This Row],[LOAN APPLICATION NO]],REPAYMENT_SCHEDULE!F:F) -> 0 | J6: =Table7[[#This Row],[TOTAL REPAYMENT]]-Table7[[#This Row],[AMOUNT PAID]] -> 650 | K6: =IF(Table7[[#This Row],[OUTSTANDING BALANCE]]=0,"Completed","Pending") -> Pending | L6: =VLOOKUP(Table7[[#This Row],[CLIENT NO]],CLIENT_MASTER!A:O,12,FALSE) -> Education | M6: =VLOOKUP(Table7[[#This Row],[CLIENT NO]],CLIENT_MASTER!A:O,11,FALSE) -> Public | N6: =VLOOKUP(Table7[[#This Row],[CLIENT NO]],CLIENT_MASTER!A:O,6,FALSE) -> Yawa P/S | P6: =VLOOKUP(Table7[[#This Row],[CLIENT NO]],CLIENT_MASTER!A:O,5,FALSE) -> 704586745 | Q6: =VLOOKUP(Table7[[#This Row],[CLIENT NO]],CLIENT_MASTER!A:O,8,FALSE) -> Jane Waiyoi | R6: =VLOOKUP(Table7[[#This Row],[CLIENT NO]],CLIENT_MASTER!A:O,9,FALSE) -> Spouse | S6: =VLOOKUP(Table7[[#This Row],[CLIENT NO]],CLIENT_MASTER!A:O,10,FALSE) -> 707967132
A7: CL-0006 | B7: Rayleen Edai | C7: LN-0006 | D7: =VLOOKUP(Table7[[#This Row],[LOAN APPLICATION NO]],LOAN_APPLICATION!A:P,4,FALSE) -> 2500 | E7: =VLOOKUP(Table7[[#This Row],[LOAN APPLICATION NO]],LOAN_APPLICATION!A:P,10,FALSE) -> 2500 | F7: =VLOOKUP(Table7[[#This Row],[LOAN APPLICATION NO]],LOAN_APPLICATION!A:P,13,FALSE) -> 0.3 | G7: =VLOOKUP(Table7[[#This Row],[LOAN APPLICATION NO]],LOAN_APPLICATION!A:P,14,FALSE) -> 2 | H7: =VLOOKUP(Table7[[#This Row],[LOAN APPLICATION NO]],LOAN_APPLICATION!A:P,15,FALSE) -> 3250 | I7: =SUMIF(REPAYMENT_SCHEDULE!B:B,Table7[[#This Row],[LOAN APPLICATION NO]],REPAYMENT_SCHEDULE!F:F) -> 0 | J7: =Table7[[#This Row],[TOTAL REPAYMENT]]-Table7[[#This Row],[AMOUNT PAID]] -> 3250 | K7: =IF(Table7[[#This Row],[OUTSTANDING BALANCE]]=0,"Completed","Pending") -> Pending | L7: =VLOOKUP(Table7[[#This Row],[CLIENT NO]],CLIENT_MASTER!A:O,12,FALSE) -> Education | M7: =VLOOKUP(Table7[[#This Row],[CLIENT NO]],CLIENT_MASTER!A:O,11,FALSE) -> Public | N7: =VLOOKUP(Table7[[#This Row],[CLIENT NO]],CLIENT_MASTER!A:O,6,FALSE) -> Teiri P/S | P7: =VLOOKUP(Table7[[#This Row],[CLIENT NO]],CLIENT_MASTER!A:O,5,FALSE) -> 706113372 | Q7: =VLOOKUP(Table7[[#This Row],[CLIENT NO]],CLIENT_MASTER!A:O,8,FALSE) -> Nelson Melu | R7: =VLOOKUP(Table7[[#This Row],[CLIENT NO]],CLIENT_MASTER!A:O,9,FALSE) -> Spouse | S7: =VLOOKUP(Table7[[#This Row],[CLIENT NO]],CLIENT_MASTER!A:O,10,FALSE) -> 708651309
A8: CL-0007 | B8: Ruth Nali | C8: LN-0007 | D8: =VLOOKUP(Table7[[#This Row],[LOAN APPLICATION NO]],LOAN_APPLICATION!A:P,4,FALSE) -> 1500 | E8: =VLOOKUP(Table7[[#This Row],[LOAN APPLICATION NO]],LOAN_APPLICATION!A:P,10,FALSE) -> 1500 | F8: =VLOOKUP(Table7[[#This Row],[LOAN APPLICATION NO]],LOAN_APPLICATION!A:P,13,FALSE) -> 0.5 | G8: =VLOOKUP(Table7[[#This Row],[LOAN APPLICATION NO]],LOAN_APPLICATION!A:P,14,FALSE) -> 4 | H8: =VLOOKUP(Table7[[#This Row],[LOAN APPLICATION NO]],LOAN_APPLICATION!A:P,15,FALSE) -> 2250 | I8: =SUMIF(REPAYMENT_SCHEDULE!B:B,Table7[[#This Row],[LOAN APPLICATION NO]],REPAYMENT_SCHEDULE!F:F) -> 0 | J8: =Table7[[#This Row],[TOTAL REPAYMENT]]-Table7[[#This Row],[AMOUNT PAID]] -> 2250 | K8: =IF(Table7[[#This Row],[OUTSTANDING BALANCE]]=0,"Completed","Pending") -> Pending | L8: =VLOOKUP(Table7[[#This Row],[CLIENT NO]],CLIENT_MASTER!A:O,12,FALSE) -> Education | M8: =VLOOKUP(Table7[[#This Row],[CLIENT NO]],CLIENT_MASTER!A:O,11,FALSE) -> Public | N8: =VLOOKUP(Table7[[#This Row],[CLIENT NO]],CLIENT_MASTER!A:O,6,FALSE) -> Teiri P/S | P8: =VLOOKUP(Table7[[#This Row],[CLIENT NO]],CLIENT_MASTER!A:O,5,FALSE) -> 702570236 | Q8: =VLOOKUP(Table7[[#This Row],[CLIENT NO]],CLIENT_MASTER!A:O,8,FALSE) -> James nali | R8: =VLOOKUP(Table7[[#This Row],[CLIENT NO]],CLIENT_MASTER!A:O,9,FALSE) -> Spouse | S8: =VLOOKUP(Table7[[#This Row],[CLIENT NO]],CLIENT_MASTER!A:O,10,FALSE) -> 707233556
A9: CL-0008 | B9: Peter Fango | C9: LN-0008 | D9: =VLOOKUP(Table7[[#This Row],[LOAN APPLICATION NO]],LOAN_APPLICATION!A:P,4,FALSE) -> 800 | E9: =VLOOKUP(Table7[[#This Row],[LOAN APPLICATION NO]],LOAN_APPLICATION!A:P,10,FALSE) -> 800 | F9: =VLOOKUP(Table7[[#This Row],[LOAN APPLICATION NO]],LOAN_APPLICATION!A:P,13,FALSE) -> 0.4 | G9: =VLOOKUP(Table7[[#This Row],[LOAN APPLICATION NO]],LOAN_APPLICATION!A:P,14,FALSE) -> 3 | H9: =VLOOKUP(Table7[[#This Row],[LOAN APPLICATION NO]],LOAN_APPLICATION!A:P,15,FALSE) -> 1120 | I9: =SUMIF(REPAYMENT_SCHEDULE!B:B,Table7[[#This Row],[LOAN APPLICATION NO]],REPAYMENT_SCHEDULE!F:F) -> 0 | J9: =Table7[[#This Row],[TOTAL REPAYMENT]]-Table7[[#This Row],[AMOUNT PAID]] -> 1120 | K9: =IF(Table7[[#This Row],[OUTSTANDING BALANCE]]=0,"Completed","Pending") -> Pending | L9: =VLOOKUP(Table7[[#This Row],[CLIENT NO]],CLIENT_MASTER!A:O,12,FALSE) -> Education | M9: =VLOOKUP(Table7[[#This Row],[CLIENT NO]],CLIENT_MASTER!A:O,11,FALSE) -> Public | N9: =VLOOKUP(Table7[[#This Row],[CLIENT NO]],CLIENT_MASTER!A:O,6,FALSE) -> Teiri P/S | P9: =VLOOKUP(Table7[[#This Row],[CLIENT NO]],CLIENT_MASTER!A:O,5,FALSE) -> 705070560 | Q9: =VLOOKUP(Table7[[#This Row],[CLIENT NO]],CLIENT_MASTER!A:O,8,FALSE) -> Rose Fango | R9: =VLOOKUP(Table7[[#This Row],[CLIENT NO]],CLIENT_MASTER!A:O,9,FALSE) -> Spouse | S9: =VLOOKUP(Table7[[#This Row],[CLIENT NO]],CLIENT_MASTER!A:O,10,FALSE) -> 702255783
A10: CL-0009 | B10: Lucy Pita | C10: LN-0009 | D10: =VLOOKUP(Table7[[#This Row],[LOAN APPLICATION NO]],LOAN_APPLICATION!A:P,4,FALSE) -> 500 | E10: =VLOOKUP(Table7[[#This Row],[LOAN APPLICATION NO]],LOAN_APPLICATION!A:P,10,FALSE) -> 500 | F10: =VLOOKUP(Table7[[#This Row],[LOAN APPLICATION NO]],LOAN_APPLICATION!A:P,13,FALSE) -> 0.2 | G10: =VLOOKUP(Table7[[#This Row],[LOAN APPLICATION NO]],LOAN_APPLICATION!A:P,14,FALSE) -> 1 | H10: =VLOOKUP(Table7[[#This Row],[LOAN APPLICATION NO]],LOAN_APPLICATION!A:P,15,FALSE) -> 600 | I10: =SUMIF(REPAYMENT_SCHEDULE!B:B,Table7[[#This Row],[LOAN APPLICATION NO]],REPAYMENT_SCHEDULE!F:F) -> 0 | J10: =Table7[[#This Row],[TOTAL REPAYMENT]]-Table7[[#This Row],[AMOUNT PAID]] -> 600 | K10: =IF(Table7[[#This Row],[OUTSTANDING BALANCE]]=0,"Completed","Pending") -> Pending | L10: =VLOOKUP(Table7[[#This Row],[CLIENT NO]],CLIENT_MASTER!A:O,12,FALSE) -> Education | M10: =VLOOKUP(Table7[[#This Row],[CLIENT NO]],CLIENT_MASTER!A:O,11,FALSE) -> Public | N10: =VLOOKUP(Table7[[#This Row],[CLIENT NO]],CLIENT_MASTER!A:O,6,FALSE) -> Teiri P/S | P10: =VLOOKUP(Table7[[#This Row],[CLIENT NO]],CLIENT_MASTER!A:O,5,FALSE) -> 706594212 | Q10: =VLOOKUP(Table7[[#This Row],[CLIENT NO]],CLIENT_MASTER!A:O,8,FALSE) -> Harry Pita | R10: =VLOOKUP(Table7[[#This Row],[CLIENT NO]],CLIENT_MASTER!A:O,9,FALSE) -> Spouse | S10: =VLOOKUP(Table7[[#This Row],[CLIENT NO]],CLIENT_MASTER!A:O,10,FALSE) -> 709491514
A11: CL-0010 | B11: Gibson Melu | C11: LN-0010 | D11: =VLOOKUP(Table7[[#This Row],[LOAN APPLICATION NO]],LOAN_APPLICATION!A:P,4,FALSE) -> 500 | E11: =VLOOKUP(Table7[[#This Row],[LOAN APPLICATION NO]],LOAN_APPLICATION!A:P,10,FALSE) -> 500 | F11: =VLOOKUP(Table7[[#This Row],[LOAN APPLICATION NO]],LOAN_APPLICATION!A:P,13,FALSE) -> 0.2 | G11: =VLOOKUP(Table7[[#This Row],[LOAN APPLICATION NO]],LOAN_APPLICATION!A:P,14,FALSE) -> 1 | H11: =VLOOKUP(Table7[[#This Row],[LOAN APPLICATION NO]],LOAN_APPLICATION!A:P,15,FALSE) -> 600 | I11: =SUMIF(REPAYMENT_SCHEDULE!B:B,Table7[[#This Row],[LOAN APPLICATION NO]],REPAYMENT_SCHEDULE!F:F) -> 0 | J11: =Table7[[#This Row],[TOTAL REPAYMENT]]-Table7[[#This Row],[AMOUNT PAID]] -> 600 | K11: =IF(Table7[[#This Row],[OUTSTANDING BALANCE]]=0,"Completed","Pending") -> Pending | L11: =VLOOKUP(Table7[[#This Row],[CLIENT NO]],CLIENT_MASTER!A:O,12,FALSE) -> Education | M11: =VLOOKUP(Table7[[#This Row],[CLIENT NO]],CLIENT_MASTER!A:O,11,FALSE) -> Public | N11: =VLOOKUP(Table7[[#This Row],[CLIENT NO]],CLIENT_MASTER!A:O,6,FALSE) -> Teiri P/S | P11: =VLOOKUP(Table7[[#This Row],[CLIENT NO]],CLIENT_MASTER!A:O,5,FALSE) -> 71720062 | Q11: =VLOOKUP(Table7[[#This Row],[CLIENT NO]],CLIENT_MASTER!A:O,8,FALSE) -> Sebby Melu | R11: =VLOOKUP(Table7[[#This Row],[CLIENT NO]],CLIENT_MASTER!A:O,9,FALSE) -> Father | S11: =VLOOKUP(Table7[[#This Row],[CLIENT NO]],CLIENT_MASTER!A:O,10,FALSE) -> 79954719

Sheet CLIENT_LOAN_HISTORY
A1: CLIENT NO | B1: CLIENT NAME | C1: TOTAL LOAN NO | D1: TOTAL LOAN AMOUNT | E1: TOTAL LOAN INTEREST PAID | F1: TOTAL LOAN DEFAULTS | G1: COMMENTS
A2: {=INDEX(CLIENT_MASTER!A:A,ROW(A2))} -> CL-0001 | B2: =VLOOKUP(A2,CLIENT_MASTER!A:R,2,FALSE) -> Camilus Dominic | C2: =COUNTIF(LOAN_APPLICATION!B:B, A2) -> 1 | D2: =SUMIF(LOAN_APPLICATION!B:B,A2,LOAN_APPLICATION!J:J) -> 1000 | E2: =SUMIF(LOAN_APPLICATION!B:B, A2, LOAN_APPLICATION!N:N) - SUMIF(LOAN_APPLICATION!B:B, A2, LOAN_APPLICATION!J:J) -> -996 | F2: =COUNTIFS(REPAYMENT_SCHEDULE!B:B,A2,REPAYMENT_SCHEDULE!H:H,"Pending") -> 0 | G2: =IF(Table9[[#This Row],[TOTAL LOAN DEFAULTS]]>0,"Needs Review","Good Standing") -> Good Standing
A3: {=INDEX(CLIENT_MASTER!A:A,ROW(A3))} -> CL-0002 | B3: =VLOOKUP(A3, CLIENT_MASTER!A:B, 2, FALSE) -> Ricky Jolgai | C3: =COUNTIF(LOAN_APPLICATION!B:B, A3) -> 1 | D3: =SUMIF(LOAN_APPLICATION!B:B,A3,LOAN_APPLICATION!J:J) -> 500 | E3: =SUMIF(LOAN_APPLICATION!B:B, A3, LOAN_APPLICATION!N:N) - SUMIF(LOAN_APPLICATION!B:B, A3, LOAN_APPLICATION!J:J) -> -499 | F3: =COUNTIFS(REPAYMENT_SCHEDULE!B:B,A3,REPAYMENT_SCHEDULE!H:H,"Pending") -> 0 | G3: =IF(Table9[[#This Row],[TOTAL LOAN DEFAULTS]]>0,"Needs Review","Good Standing") -> Good Standing
A4: {=INDEX(CLIENT_MASTER!A:A,ROW(A4))} -> CL-0003 | B4: =VLOOKUP(A4, CLIENT_MASTER!A:B, 2, FALSE) -> Simeon Kaipo | C4: =COUNTIF(LOAN_APPLICATION!B:B, A4) -> 1 | D4: =SUMIF(LOAN_APPLICATION!B:B,A4,LOAN_APPLICATION!J:J) -> 1500 | E4: =SUMIF(LOAN_APPLICATION!B:B, A4, LOAN_APPLICATION!N:N) - SUMIF(LOAN_APPLICATION!B:B, A4, LOAN_APPLICATION!J:J) -> -1499 | F4: =COUNTIFS(REPAYMENT_SCHEDULE!B:B,A4,REPAYMENT_SCHEDULE!H:H,"Pending") -> 0 | G4: =IF(Table9[[#This Row],[TOTAL LOAN DEFAULTS]]>0,"Needs Review","Good Standing") -> Good Standing
A5: {=INDEX(CLIENT_MASTER!A:A,ROW(A5))} -> CL-0004 | B5: =VLOOKUP(A5, CLIENT_MASTER!A:B, 2, FALSE) -> Josek Yuwal | C5: =COUNTIF(LOAN_APPLICATION!B:B, A5) -> 1 | D5: =SUMIF(LOAN_APPLICATION!B:B,A5,LOAN_APPLICATION!J:J) -> 800 | E5: =SUMIF(LOAN_APPLICATION!B:B, A5, LOAN_APPLICATION!N:N) - SUMIF(LOAN_APPLICATION!B:B, A5, LOAN_APPLICATION!J:J) -> -797 | F5: =COUNTIFS(REPAYMENT_SCHEDULE!B:B,A5,REPAYMENT_SCHEDULE!H:H,"Pending") -> 0 | G5: =IF(Table9[[#This Row],[TOTAL LOAN DEFAULTS]]>0,"Needs Review","Good Standing") -> Good Standing
A6: {=INDEX(CLIENT_MASTER!A:A,ROW(A6))} -> CL-0005 | B6: =VLOOKUP(A6, CLIENT_MASTER!A:B, 2, FALSE) -> Bob Waiyoi | C6: =COUNTIF(LOAN_APPLICATION!B:B, A6) -> 1 | D6: =SUMIF(LOAN_APPLICATION!B:B,A6,LOAN_APPLICATION!J:J) -> 500 | E6: =SUMIF(LOAN_APPLICATION!B:B, A6, LOAN_APPLICATION!N:N) - SUMIF(LOAN_APPLICATION!B:B, A6, LOAN_APPLICATION!J:J) -> -498 | F6: =COUNTIFS(REPAYMENT_SCHEDULE!B:B,A6,REPAYMENT_SCHEDULE!H:H,"Pending") -> 0 | G6: =IF(Table9[[#This Row],[TOTAL LOAN DEFAULTS]]>0,"Needs Review","Good Standing") -> Good Standing
A7: {=INDEX(CLIENT_MASTER!A:A,ROW(A7))} -> CL-0006 | B7: =VLOOKUP(A7, CLIENT_MASTER!A:B, 2, FALSE) -> Rayleen Edai | C7: =COUNTIF(LOAN_APPLICATION!B:B, A7) -> 1 | D7: =SUMIF(LOAN_APPLICATION!B:B,A7,LOAN_APPLICATION!J:J) -> 2500 | E7: =SUMIF(LOAN_APPLICATION!B:B, A7, LOAN_APPLICATION!N:N) - SUMIF(LOAN_APPLICATION!B:B, A7, LOAN_APPLICATION!J:J) -> -2498 | F7: =COUNTIFS(REPAYMENT_SCHEDULE!B:B,A7,REPAYMENT_SCHEDULE!H:H,"Pending") -> 0 | G7: =IF(Table9[[#This Row],[TOTAL LOAN DEFAULTS]]>0,"Needs Review","Good Standing") -> Good Standing
A8: {=INDEX(CLIENT_MASTER!A:A,ROW(A8))} -> CL-0007 | B8: =VLOOKUP(A8, CLIENT_MASTER!A:B, 2, FALSE) -> Ruth Nali | C8: =COUNTIF(LOAN_APPLICATION!B:B, A8) -> 1 | D8: =SUMIF(LOAN_APPLICATION!B:B,A8,LOAN_APPLICATION!J:J) -> 1500 | E8: =SUMIF(LOAN_APPLICATION!B:B, A8, LOAN_APPLICATION!N:N) - SUMIF(LOAN_APPLICATION!B:B, A8, LOAN_APPLICATION!J:J) -> -1496 | F8: =COUNTIFS(REPAYMENT_SCHEDULE!B:B,A8,REPAYMENT_SCHEDULE!H:H,"Pending") -> 0 | G8: =IF(Table9[[#This Row],[TOTAL LOAN DEFAULTS]]>0,"Needs Review","Good Standing") -> Good Standing
A9: {=INDEX(CLIENT_MASTER!A:A,ROW(A9))} -> CL-0008 | B9: =VLOOKUP(A9, CLIENT_MASTER!A:B, 2, FALSE) -> Peter Fango | C9: =COUNTIF(LOAN_APPLICATION!B:B, A9) -> 1 | D9: =SUMIF(LOAN_APPLICATION!B:B,A9,LOAN_APPLICATION!J:J) -> 800 | E9: =SUMIF(LOAN_APPLICATION!B:B, A9, LOAN_APPLICATION!N:N) - SUMIF(LOAN_APPLICATION!B:B, A9, LOAN_APPLICATION!J:J) -> -797 | F9: =COUNTIFS(REPAYMENT_SCHEDULE!B:B,A9,REPAYMENT_SCHEDULE!H:H,"Pending") -> 0 | G9: =IF(Table9[[#This Row],[TOTAL LOAN DEFAULTS]]>0,"Needs Review","Good Standing") -> Good Standing
A10: {=INDEX(CLIENT_MASTER!A:A,ROW(A10))} -> CL-0009 | B10: =VLOOKUP(A10, CLIENT_MASTER!A:B, 2, FALSE) -> Lucy Pita | C10: =COUNTIF(LOAN_APPLICATION!B:B, A10) -> 1 | D10: =SUMIF(LOAN_APPLICATION!B:B,A10,LOAN_APPLICATION!J:J) -> 500 | E10: =SUMIF(LOAN_APPLICATION!B:B, A10, LOAN_APPLICATION!N:N) - SUMIF(LOAN_APPLICATION!B:B, A10, LOAN_APPLICATION!J:J) -> -499 | F10: =COUNTIFS(REPAYMENT_SCHEDULE!B:B,A10,REPAYMENT_SCHEDULE!H:H,"Pending") -> 0 | G10: =IF(Table9[[#This Row],[TOTAL LOAN DEFAULTS]]>0,"Needs Review","Good Standing") -> Good Standing
A11: {=INDEX(CLIENT_MASTER!A:A,ROW(A11))} -> CL-0010 | B11: =VLOOKUP(A11, CLIENT_MASTER!A:B, 2, FALSE) -> Gibson Melu | C11: =COUNTIF(LOAN_APPLICATION!B:B, A11) -> 1 | D11: =SUMIF(LOAN_APPLICATION!B:B,A11,LOAN_APPLICATION!J:J) -> 500 | E11: =SUMIF(LOAN_APPLICATION!B:B, A11, LOAN_APPLICATION!N:N) - SUMIF(LOAN_APPLICATION!B:B, A11, LOAN_APPLICATION!J:J) -> -499 | F11: =COUNTIFS(REPAYMENT_SCHEDULE!B:B,A11,REPAYMENT_SCHEDULE!H:H,"Pending") -> 0 | G11: =IF(Table9[[#This Row],[TOTAL LOAN DEFAULTS]]>0,"Needs Review","Good Standing") -> Good Standing
